omniblack/email_to_chat/__init__.py
omniblack/email_to_chat/__main__.py
omniblack/email_to_chat/async_utils.py
omniblack/email_to_chat/creds.py
omniblack/email_to_chat/discord_sink.py
omniblack/email_to_chat/email_sink.py
omniblack/email_to_chat/heartbeat_sink.py
omniblack/email_to_chat/internal_sink.py
omniblack/email_to_chat/model.py
omniblack/email_to_chat/msg_queue.py
omniblack.email_to_chat-0.2.3.dist-info/entry_points.txt
omniblack.email_to_chat-0.2.3.dist-info/WHEEL
omniblack.email_to_chat-0.2.3.dist-info/METADATA
omniblack.email_to_chat-0.2.3.dist-info/RECORD
